anydatalib/__init__.py
anydatalib/func.py
tests/__init__.py
tests/test_func.py
anydatalib-0.1.0.dist-info/METADATA
anydatalib-0.1.0.dist-info/WHEEL
anydatalib-0.1.0.dist-info/top_level.txt
anydatalib-0.1.0.dist-info/RECORD
