Metadata-Version: 2.1
Name: anydatalib
Version: 0.1.0
Summary: anydata library
Home-page: UNKNOWN
Author: anydata
License: anydata
Platform: UNKNOWN
